ipymd/__init__.py
ipymd/core/__init__.py
ipymd/core/contents_manager.py
ipymd/core/format_manager.py
ipymd/core/prompt.py
ipymd/core/scripts.py
ipymd/core/tests/__init__.py
ipymd/core/tests/test_core.py
ipymd/core/tests/test_prompt.py
ipymd/core/tests/test_scripts.py
ipymd/ext/__init__.py
ipymd/ext/six.py
ipymd/formats/__init__.py
ipymd/formats/atlas.py
ipymd/formats/markdown.py
ipymd/formats/notebook.py
ipymd/formats/opendocument.py
ipymd/formats/python.py
ipymd/formats/tests/__init__.py
ipymd/formats/tests/_utils.py
ipymd/formats/tests/test_atlas.py
ipymd/formats/tests/test_markdown.py
ipymd/formats/tests/test_notebook.py
ipymd/formats/tests/test_opendocument.py
ipymd/formats/tests/test_python.py
ipymd/formats/tests/test_utils.py
ipymd/lib/__init__.py
ipymd/lib/base_lexer.py
ipymd/lib/markdown.py
ipymd/lib/opendocument.py
ipymd/lib/python.py
ipymd/lib/tests/__init__.py
ipymd/lib/tests/test_base_lexer.py
ipymd/lib/tests/test_markdown.py
ipymd/lib/tests/test_opendocument.py
ipymd/lib/tests/test_python.py
ipymd/utils/__init__.py
ipymd/utils/tempdir.py
ipymd/utils/utils.py
ipymd/utils/tests/__init__.py
ipymd/utils/tests/test_tempdir.py
ipymd/utils/tests/test_utils.py
ipymd-0.1.3.dist-info/DESCRIPTION.rst
ipymd-0.1.3.dist-info/METADATA
ipymd-0.1.3.dist-info/RECORD
ipymd-0.1.3.dist-info/WHEEL
ipymd-0.1.3.dist-info/entry_points.txt
ipymd-0.1.3.dist-info/metadata.json
ipymd-0.1.3.dist-info/top_level.txt
