Metadata-Version: 2.0
Name: ipymd
Version: 0.1.3
Summary: Use the IPython notebook as an interactive Markdown editor
Home-page: https://github.com/rossant/ipymd
Author: Cyrille Rossant
Author-email: cyrille.rossant at gmail.com
License: BSD
Platform: UNKNOWN
Classifier: Development Status :: 3 - Alpha
Classifier: License :: OSI Approved :: BSD License
Classifier: Environment :: Console
Classifier: Framework :: IPython
Classifier: Intended Audience :: Developers
Classifier: Natural Language :: English
Classifier: Operating System :: Unix
Classifier: Operating System :: POSIX
Classifier: Operating System :: MacOS :: MacOS X
Classifier: Programming Language :: Python
Classifier: Programming Language :: Python :: 2
Classifier: Programming Language :: Python :: 2.7
Classifier: Programming Language :: Python :: 3
Classifier: Programming Language :: Python :: 3.3
Classifier: Programming Language :: Python :: 3.4
Classifier: Topic :: Software Development :: Libraries
Classifier: Topic :: Text Processing :: Markup
Requires-Dist: pyyaml
Provides-Extra: odf
Requires-Dist: odfpy; extra == 'odf'
